hydropy/__init__.py
hydropy/baseflow.py
hydropy/exceptions.py
hydropy/flowanalysis.py
hydropy/ipython.py
hydropy/old_tests.py
hydropy/reading_third_party_data.py
hydropy/storm.py
hydropy-0.1.2.dist-info/DESCRIPTION.rst
hydropy-0.1.2.dist-info/METADATA
hydropy-0.1.2.dist-info/RECORD
hydropy-0.1.2.dist-info/WHEEL
hydropy-0.1.2.dist-info/metadata.json
hydropy-0.1.2.dist-info/top_level.txt
